bitwarden_keyring/__init__.py
bitwarden_keyring-0.3.1.dist-info/LICENSE.md
bitwarden_keyring-0.3.1.dist-info/METADATA
bitwarden_keyring-0.3.1.dist-info/WHEEL
bitwarden_keyring-0.3.1.dist-info/entry_points.txt
bitwarden_keyring-0.3.1.dist-info/top_level.txt
bitwarden_keyring-0.3.1.dist-info/zip-safe
bitwarden_keyring-0.3.1.dist-info/RECORD
