Metadata-Version: 2.1
Name: bitwarden-keyring
Version: 0.3.1
Summary: Keyring backend reading password data from Bitwarden
Home-page: https://github.com/ewjoachim/bitwarden-keyring
Author: Joachim Jablon
Author-email: ewjoachim@gmail.com
License: Apache Software License
Keywords: bitwarden keyring password
Classifier: Development Status :: 4 - Beta
Classifier: Intended Audience :: Developers
Classifier: License :: OSI Approved :: MIT License
Classifier: Programming Language :: Python :: 3
License-File: LICENSE.md
Requires-Dist: keyring
Provides-Extra: dev
Requires-Dist: flake8 ; extra == 'dev'
Requires-Dist: isort ; extra == 'dev'
Requires-Dist: black ; extra == 'dev'
Requires-Dist: pytest ; extra == 'dev'
Requires-Dist: pytest-mock ; extra == 'dev'
Requires-Dist: pytest-cov ; extra == 'dev'
